uws/__init__.py
uws/admin.py
uws/apps.py
uws/classes.py
uws/client.py
uws/database_router.py
uws/models.py
uws/permissions.py
uws/serializers.py
uws/tasks.py
uws/urls.py
uws/views.py
uws/workers.py
uws/migrations/0001_initial.py
uws/migrations/0002_jobtoken.py
uws/migrations/__init__.py
uws/static/uws/.gitkeep
uws/templates/uws/.gitkeep
django_uws-0.2.dev370864.dist-info/LICENSE
django_uws-0.2.dev370864.dist-info/METADATA
django_uws-0.2.dev370864.dist-info/WHEEL
django_uws-0.2.dev370864.dist-info/top_level.txt
django_uws-0.2.dev370864.dist-info/RECORD
